{
	"id": 108691866,
	"name": "Jax Circles",
	"author": "GDFigures",
	"creators": [
		"GDFigures"
	],
	"verifier": "GDFigures",
	"verification": "https://youtu.be/i3WkjQypX9s",
	"percentToQualify": 100,
	"password": "No Copy",
	"records": [
		{
			"user": "m3nt411",
			"link": "https://youtu.be/q56H-tCmQjw?si=SATcH6cD6DO0kzmT",
			"percent": 100,
			"hz": 360
		},
		{
			"user": "Kendrick West",
			"link": "https://www.youtube.com/watch?v=zWz4vafFipQ",
			"percent": 100,
			"hz": 360
		},
		{
			"user": "staticon",
			"link": "https://youtu.be/2sz1U0TNPZ4",
			"percent": 100,
			"hz": 360
		},
		{
			"user": "Jarzst",
			"link": "https://www.youtube.com/watch?v=T84VoHShiAc",
			"percent": 100,
			"hz": 360
		},
		{
			"user": "shafikdabest",
			"link": "https://www.youtube.com/live/eu2c65gEVi4?si=YRkuXmt0DEiC9QDW",
			"percent": 100,
			"hz": 360
		}
	]
}