{
	"id": 108457830,
	"name": "Skibidi Pomni X",
	"author": "Czila",
	"creators": [
		"Czila"
	],
	"verifier": "czila",
	"verification": "https://www.youtube.com/watch?v=4k0XRe1BysA",
	"percentToQualify": "100",
	"password": "None",
	"records": [
		{
			"user": "NojusGamingg",
			"link": "https://www.youtube.com/watch?v=psTLVztnGzo",
			"percent": 100,
			"hz": 360
		},
		{
			"user": "gdyakob",
			"link": "https://youtu.be/46qBiyfDRlI?si=7lufvBrm3ckAcW6H",
			"percent": 100,
			"hz": 360
		},
		{
			"user": "adongus",
			"link": "https://youtu.be/NkoFUrgxgO4",
			"percent": 100,
			"hz": 360
		},
		{
			"user": "Specie",
			"link": "https://www.youtube.com/watch?v=QAme3L0LwfQ",
			"percent": 100,
			"hz": 360
		},
		{
			"user": "heolo",
			"link": "https://youtu.be/_IaaAxVPabk",
			"percent": 100,
			"hz": 360
		},
		{
			"user": "Montrix",
			"link": "https://youtu.be/RnrQIhwsaJU",
			"percent": 100,
			"hz": 360
		},
		{
			"user": "Aphoem",
			"link": "https://www.youtube.com/watch?v=_2uumd-hgXQ",
			"percent": 100,
			"hz": 360
		},
		{
			"user": "Water",
			"link": "https://www.youtube.com/watch?v=3PzG1zSEFJM",
			"percent": 100,
			"hz": 360
		},
		{
			"user": "m3nt411",
			"link": "https://youtu.be/midKsCCS7-k?si=4Bb5VODkvq-OwWVj",
			"percent": 100,
			"hz": 360
		},
		{
			"user": "Kendrick West",
			"link": "https://youtu.be/MwJUA9LROTY",
			"percent": 100,
			"hz": 360
		},
		{
			"user": "Deathrange",
			"link": "https://youtu.be/hhEBH2zoHqs",
			"percent": 100,
			"hz": 360
		},
		{
			"user": "staticon",
			"link": "https://youtu.be/2sz1U0TNPZ4",
			"percent": 100,
			"hz": 360
		},
		{
			"user": "MimoGD",
			"link": "https://youtu.be/R59JhF8YFFE",
			"percent": 100,
			"hz": 360
		},
		{
			"user": "MetroZ",
			"link": "https://www.youtube.com/watch?v=OsLjFplAhwI",
			"percent": 100,
			"hz": 360
		},
		{
			"user": "sonofnooby",
			"link": "https://youtu.be/pTNqiC9NTio",
			"percent": 100,
			"hz": 360
		},
		{
			"user": "Jarzst",
			"link": "https://youtu.be/n8JzAADVkwE",
			"percent": 100,
			"hz": 360
		},
		{
			"user": "MacacoChucrut",
			"link": "https://youtu.be/3Zk9_zuFwvs",
			"percent": 100,
			"hz": 360
		}
	]
}